dame_sexo/__init__.py
dame_sexo/dame_sexo.pickle
dame_sexo/female.txt
dame_sexo/gender.py
dame_sexo/male.txt
dame_sexo-0.0.4.dist-info/METADATA
dame_sexo-0.0.4.dist-info/WHEEL
dame_sexo-0.0.4.dist-info/license.txt
dame_sexo-0.0.4.dist-info/top_level.txt
dame_sexo-0.0.4.dist-info/RECORD
