Metadata-Version: 2.1
Name: dame-sexo
Version: 0.0.4
Summary: Determines sex gender based on first name
Author: Luis Vivas
Author-email: luisvivas@gmail.com
License: UNKNOWN
Platform: UNKNOWN
Classifier: Programming Language :: Python :: 3
Classifier: License :: OSI Approved :: MIT License
Classifier: Operating System :: OS Independent
Requires-Python: >=3.7
License-File: license.txt
